suffix_printer.py
suffix_printer-0.0.5.dist-info/DESCRIPTION.rst
suffix_printer-0.0.5.dist-info/METADATA
suffix_printer-0.0.5.dist-info/RECORD
suffix_printer-0.0.5.dist-info/WHEEL
suffix_printer-0.0.5.dist-info/metadata.json
suffix_printer-0.0.5.dist-info/top_level.txt
