Metadata-Version: 2.0
Name: suffix-printer
Version: 0.0.5
Summary: Python module supporting printing of suffixed strings.
Home-page: https://github.com/arch4ngel/suffix_printer
Author: Justin Angel
Author-email: justinangel86@gmail.com
License: UNKNOWN
Platform: UNKNOWN
Classifier: Development Status :: 3 - Alpha
Classifier: Intended Audience :: Developers
Classifier: Topic :: Software Development :: Build Tools
Classifier: License :: OSI Approved :: MIT License
Classifier: Programming Language :: Python :: 3.6
